core/__init__.py
core/factory.py
core/helpers/__init__.py
core/helpers/constants.py
core/helpers/functions.py
core/serializers/__init__.py
core/serializers/jsonserializer.py
core/serializers/xmlserializer.py
custom_json_serializer_1234-1.6.dist-info/METADATA
custom_json_serializer_1234-1.6.dist-info/WHEEL
custom_json_serializer_1234-1.6.dist-info/top_level.txt
custom_json_serializer_1234-1.6.dist-info/RECORD
